versatool/__init__.py
versatool/webkit.py
versatool-0.0.1.dist-info/licenses/LICENSE
versatool-0.0.1.dist-info/METADATA
versatool-0.0.1.dist-info/WHEEL
versatool-0.0.1.dist-info/top_level.txt
versatool-0.0.1.dist-info/RECORD
