Metadata-Version: 2.4
Name: VersaTool
Version: 0.0.1
Summary: VersaTool is a lightweight Python utility library that helps you write less code and do more, by simplifying common patterns and wrapping popular Python libraries with cleaner syntax.
Author: Mahdi Mohammadiha
License: AGPL-3.0
Project-URL: Homepage, https://github.com/MahdiMohammadiha/VersaTool
License-File: LICENSE
Requires-Dist: selenium
Dynamic: license-file
